{"label": "fake", "id": "4488651448313689", "date": "2020-03-31 21:29", "user_name": "任花花er", "user_id": "3289964410", "text": "什么...出关要隔离为了不隔离从澳门游泳回珠海哈哈哈哈哈体力好哟。快点游，海关在岸上等你 L任花花er的微博视频 ​​​​", "pic_url": [], "video_url": "http://f.video.weibocdn.com/004h3f4bgx07C8wGXfIz010412002iXd0E010.mp4?label=mp4_hd&template=384x640.24.0&trans_finger=6038099a530779e853bb78b617dbd3ab&media_id=4488651393138700&tp=8x8A3El:YTkl0eM8&us=0&ori=1&bf=4&ot=v&lp=0000hUDeH&ps=4pdsh0&uid=3vCCKw&ab=966-g1&Expires=1599324265&ssig=6CB3re69uf&KID=unistore,video&480", "comments_num": "2", "repost_num": "1", "like_num": "1", "comments": [{"id": "4488910124515888", "date": "2020-04-1 14:37", "user_name": "发烧感冒你最开心", "user_id": "3682490375", "text": "：辟谣了", "pic_url": ""}, {"id": "4488826749803942", "date": "2020-04-1 09:05", "user_name": "我是阿诺舒华辛力加", "user_id": "2945655657", "text": "：这是昨天的吗", "pic_url": ""}], "reposts": [{"id": "4488734365798334", "date": "2020-04-1 02:58", "user_name": "用户6171347160", "user_id": "6171347160", "text": "转发微博", "pic_url": []}]}