{"label": "fake", "id": "4501893030213552", "date": "2020-05-07 10:26", "user_id": "265a1eb8254bc75fbe4a6667d15737b0", "text": "祸不单行，美国确诊123万，刚刚凌晨化工厂大爆炸，近6万人受灾，上帝也要惩罚美利坚了吗？​#今日热搜头条# 美国国内疫情严重，够特朗普喝一壶的，还有心思到处惹是生非，甩锅侮辱中国，在中东波斯湾搞事情，威胁伊朗，粗暴干扰他国内政。​人在做天在看，美国得克萨斯州，凌晨一点，一座化工厂发生严重爆炸，火光四起，巨大火光震动波及到数公里之外的居民，到目前为止，已知10人被玻璃划伤，数名工人伤亡。​只隔几小时又发生第二波爆炸，引起惊恐万分，5.4万居民连夜紧急撤退。到现在为止，究竟是天灾还是人祸，不得而知，但是爆炸释放出来的有毒气体，已经袭击无数市民。​似乎是上帝在提醒美国，不要搞事情，挑起战乱，制造事端，先管理好自己千疮百孔的国家。#吐槽#", "pic_url": ["https://wx2.sinaimg.cn/thumb150/006nW7Xigy1gejodsyk0gj30hs09wq3d.jpg", "https://wx3.sinaimg.cn/thumb150/006nW7Xigy1gejodtc4doj30hs09m3z6.jpg", "https://wx4.sinaimg.cn/thumb150/006nW7Xigy1gejodu8memj30dw086js5.jpg"], "video_url": "", "comment_num": "14", "repost_num": "5", "like_num": "20", "comments": [{"id": "4501956787300443", "date": "2020-05-07 14:40", "user_id": "07a39c7daf7d849f353edc3cd8410609", "text": "：多行不义必自毙", "pic_url": ""}, {"id": "4501893050562718", "date": "2020-05-07 10:26", "user_id": "df58b6ad714b953bf6aa50f46d2b537e", "text": "：“独立生活 没有人会为你遮风挡雨” ???", "pic_url": ""}, {"id": "4501899573578145", "date": "2020-05-07 10:52", "user_id": "ff8f076868aadf666e05747caa14bb7b", "text": "：顶上去", "pic_url": ""}, {"id": "4501894901397952", "date": "2020-05-07 10:34", "user_id": "da69a0b90c4129ec189af2bf7de917a4", "text": "：", "pic_url": ""}, {"id": "4501894683446508", "date": "2020-05-07 10:33", "user_id": "2f4fcb956dbbd7e48db0496ba9e1375b", "text": "：上午好", "pic_url": ""}, {"id": "4501893835799260", "date": "2020-05-07 10:29", "user_id": "8c0408c55f47a11bd5c6cc2cf77dbc79", "text": "：历害", "pic_url": ""}, {"id": "4501893068144285", "date": "2020-05-07 10:26", "user_id": "d161e9d72226b79241ec5cd9e22b5f42", "text": "：特地来看望博主了", "pic_url": ""}, {"id": "4501955013122074", "date": "2020-05-07 14:32", "user_id": "c7db03467943751aae9001ae30ee30e1", "text": "：之前不是说中国厂房着火是为了骗保险费！现在学师傅了？要搞就搞个大的？", "pic_url": ""}, {"id": "4501895299590736", "date": "2020-05-07 10:35", "user_id": "4b9023fe89fc63484622cc9ab4a4482c", "text": "：厉害了", "pic_url": ""}, {"id": "4502059683035115", "date": "2020-05-07 21:28", "user_id": "dab26934cbf6481e3137c058cdc6b0b8", "text": "：民众是无辜的", "pic_url": ""}, {"id": "4501894112658016", "date": "2020-05-07 10:31", "user_id": "41c7da818eeaf23ae7fb77ac379092c3", "text": "：学易多年未曾休，雪染双鬓使人忧；弘扬国粹成大业，中华文明不可丢。", "pic_url": ""}], "reposts": [{"id": "4501912671766888", "date": "2020-05-07 11:44", "user_id": "5c3c2420d4956f7b36bbba3de5dde431", "text": "快转微博", "pic_url": []}, {"id": "4501903386487803", "date": "2020-05-07 11:07", "user_id": "59d2a3e995d098d43048dc56008daac2", "text": "转发微博", "pic_url": []}, {"id": "4501903302108208", "date": "2020-05-07 11:07", "user_id": "e1b710e1963409d1e377810c428b3594", "text": "转发微博", "pic_url": []}, {"id": "4501897425834898", "date": "2020-05-07 10:44", "user_id": "764c9239345c73886992e1af37a5d27d", "text": "快转微博", "pic_url": []}, {"id": "4501896444500420", "date": "2020-05-07 10:40", "user_id": "fc992a3a441e2466f15d573519baac48", "text": "快转微博", "pic_url": []}]}