{"label": "fake", "id": "7f63b1a8e534cefe7a7d88d530f31838", "date": "2020-03-02 07:07", "user_id": "dd1adfad1f947d0b2c22d271db5ef976", "text": "《“我不是中国人”，华人女子获美国绿卡，慷慨对美捐赠20万只口罩》此视频已有6万次播放，快来一起看看！O网页链接 ​​​​", "pic_url": [], "video_url": "", "comment_num": "1", "repost_num": "1", "like_num": "1", "analysis": "经查，此微博称“女子慷慨对美捐赠20万只口罩，并称已经获得美国绿卡，即将加入美国国籍，现在已经不是中国人”等内容不实，据@宁波晚报：漏洞百出！系造谣。详情：https://weibo.com/1938523582/IwMiLFyoF，被举报人言论构成“发布不实信息”，且情节恶劣。现根据《微博举报投诉操作细则》（<http://service.account.weibo.com/roles/guiding>）第19条，对被举报人处理如下：扣除信用积分5分，禁言7天，禁被关注7天。上述处理在公布后60分钟内生效。", "comments": [{"id": "8618136cefbdce6827ef985c461dafe3", "date": "2020-03-02 08:09", "user_id": "dd1adfad1f947d0b2c22d271db5ef976", "text": "：花300百万美元，并且把身体倒贴给穷瘪三玩，获得美国绿卡后大势渲染，这种臭货不值得评论，可以肯定的是它离瘪三的日子不会太远。", "pic_url": ""}], "reposts": []}